spark_mec_bp/__init__.py
spark_mec_bp/application/__init__.py
spark_mec_bp/application/app.py
spark_mec_bp/application/models.py
spark_mec_bp/application/test_data/input_data.asc
spark_mec_bp/calculators/__init__.py
spark_mec_bp/calculators/atom_concentration.py
spark_mec_bp/calculators/electron_concetration.py
spark_mec_bp/calculators/intensity_ratios.py
spark_mec_bp/calculators/ion_atom_concentration.py
spark_mec_bp/calculators/temperature.py
spark_mec_bp/calculators/total_concentration.py
spark_mec_bp/calculators/voigt_integrals.py
spark_mec_bp/data_preparation/__init__.py
spark_mec_bp/data_preparation/getters/__init__.py
spark_mec_bp/data_preparation/getters/atomic_lines_data_getter.py
spark_mec_bp/data_preparation/getters/ionization_energy_data_getter.py
spark_mec_bp/data_preparation/getters/partition_function_data_getter.py
spark_mec_bp/lib/__init__.py
spark_mec_bp/lib/peak_finder.py
spark_mec_bp/lib/spectrum_corrector.py
spark_mec_bp/logger/__init__.py
spark_mec_bp/logger/logger.py
spark_mec_bp/nist/__init__.py
spark_mec_bp/nist/fetchers/__init__.py
spark_mec_bp/nist/fetchers/atomic_levels.py
spark_mec_bp/nist/fetchers/atomic_lines.py
spark_mec_bp/nist/fetchers/ionization_energy.py
spark_mec_bp/nist/parsers/__init__.py
spark_mec_bp/nist/parsers/atomic_levels.py
spark_mec_bp/nist/parsers/atomic_lines.py
spark_mec_bp/nist/parsers/ionization_energy.py
spark_mec_bp/nist/validators/__init__.py
spark_mec_bp/nist/validators/response_error.py
spark_mec_bp/plotting/__init__.py
spark_mec_bp/plotting/plotter.py
spark_mec_bp/readers/__init__.py
spark_mec_bp/readers/ascii_reader.py
spark_mec_bp/validation/__init__.py
spark_mec_bp/validation/line_pair_checker.py
spark_mec_bp-0.1.2.dist-info/LICENSE
spark_mec_bp-0.1.2.dist-info/METADATA
spark_mec_bp-0.1.2.dist-info/WHEEL
spark_mec_bp-0.1.2.dist-info/top_level.txt
spark_mec_bp-0.1.2.dist-info/RECORD
