Metadata-Version: 2.1
Name: spark-mec-bp
Version: 0.1.2
Summary: Spark Multi-element Combinatory Boltzmann Plots
Author-email: Attila Kohut <akohut@titan.physx.u-szeged.hu>, Gergely Kohut <kohut.gergely@gmail.com>
License: BSD-3-Clause
Project-URL: source, https://github.com/kohutgergely/spark-mec-bp
Classifier: Intended Audience :: Science/Research
Classifier: Topic :: Scientific/Engineering
Classifier: License :: OSI Approved :: BSD License
Classifier: Operating System :: OS Independent
Classifier: Programming Language :: Python :: 3
Classifier: Programming Language :: Python :: 3 :: Only
Classifier: Programming Language :: Python :: 3.7
Classifier: Programming Language :: Python :: 3.8
Classifier: Programming Language :: Python :: 3.9
Classifier: Programming Language :: Python :: 3.10
Requires-Python: >=3.7
License-File: LICENSE
Requires-Dist: requests >=2.27.0
Requires-Dist: beautifulsoup4 >=4.11.0
Requires-Dist: pandas >=1.3.5
Requires-Dist: numpy >=1.21.6
Requires-Dist: scipy >=1.7.3
Requires-Dist: matplotlib >=3.5.3
Requires-Dist: lmfit >=1.2.1
